DP700/__init__.py
DP700/aqctl_DP700.py
DP700/dpPort.py
DP700/driver.py
DP700-0.1.dist-info/LICENSE.txt
DP700-0.1.dist-info/METADATA
DP700-0.1.dist-info/WHEEL
DP700-0.1.dist-info/entry_points.txt
DP700-0.1.dist-info/top_level.txt
DP700-0.1.dist-info/RECORD
