Metadata-Version: 2.1
Name: DP700
Version: 0.1
Summary: ARTIQ support for RIGOL DP700 series power supplies
Home-page: https://github.com/ARTIQ-Controllers/DP700
Author: OregonIons
License: LGPLv3+
Download-URL: https://github.com/ARTIQ-Controllers/DP700
Platform: UNKNOWN
Classifier: Programming Language :: Python :: 3
Classifier: License :: OSI Approved :: GNU Lesser General Public License v3 or later (LGPLv3+)
Classifier: Operating System :: OS Independent
Requires-Python: >=3.5
Requires-Dist: sipyco
Requires-Dist: pyserial
